[
    {
        "Title": "Across the Universe",
        "Plot": "The music of The Beatles and the Vietnam War form the backdrop for the romance between an upper-class American girl and a poor Liverpudlian artist.",
        "Genre": "Drama, Fantasy, History",
        "Year": 2007,
        "Actors": "Evan Rachel Wood, Jim Sturgess, Joe Anderson",
        "Director": "Julie Taymore",
        "imdbID": "tt0445922"
    },
    {
        "Title": "Interstellar",
        "Plot": "When Earth becomes uninhabitable in the future, a farmer and ex-NASA pilot, Joseph Cooper, is tasked to pilot a spacecraft, along with a team of researchers, to find a new planet for humans.",
        "Genre": "Adventure, Drama, Sci-Fi",
        "Year": 2014,
        "Actors": "Matthew McConaughey, Anne Hathaway, Jessica Chastain",
        "Director": "Christopher Nolan",
        "imdbID": "tt0816692"
    },
    {
        "Title": "Toy Story",
        "Plot": "A cowboy doll is profoundly threatened and jealous when a new spaceman action figure supplants him as top toy in a boy's bedroom.",
        "Genre": "Animation, Adventure, Comedy",
        "Year": 1995,
        "Actors": "Tom Hanks, Tim Allen, Don Rickles",
        "Director": "Directorman",
        "imdbID": "tt0114709"
    },
    {
        "Title": "Star Trek",
        "Plot": "The brash James T. Kirk tries to live up to his father's legacy with Mr. Spock keeping him in check as a vengeful Romulan from the future creates black holes to destroy the Federation one planet at a time.",
        "Genre": "Action, Adventure, Sci-Fi",
        "Year": 2009,
        "Actors": "Chris Pine, Zachary Quinto, Simon Pegg",
        "Director": "J.J. Abrams",
        "imdbID": "tt0796366"
    }
]